streamlit_search_data_visualization/__init__.py
streamlit_search_data_visualization/base_plot.py
streamlit_search_data_visualization/filter.py
streamlit_search_data_visualization/overview.py
streamlit_search_data_visualization/parallel_coordinates.py
streamlit_search_data_visualization/scatter_2d.py
streamlit_search_data_visualization/scatter_3d.py
streamlit_search_data_visualization/scatter_matrix.py
streamlit_search_data_visualization/surface_3d.py
streamlit_search_data_visualization-0.0.4.dist-info/METADATA
streamlit_search_data_visualization-0.0.4.dist-info/WHEEL
streamlit_search_data_visualization-0.0.4.dist-info/top_level.txt
streamlit_search_data_visualization-0.0.4.dist-info/RECORD
