Metadata-Version: 2.1
Name: streamlit-search-data-visualization
Version: 0.0.4
Home-page: https://github.com/SimonBlanke/common-search-data-visualization
Author: Simon Blanke
Author-email: simon.blanke@yahoo.com
License: MIT
Keywords: data-science
Classifier: Programming Language :: Python :: 3
Classifier: Programming Language :: Python :: 3.5
Classifier: Programming Language :: Python :: 3.6
Classifier: Programming Language :: Python :: 3.7
Classifier: License :: OSI Approved :: MIT License
Classifier: Operating System :: OS Independent
Classifier: Topic :: Scientific/Engineering :: Information Analysis
Classifier: Topic :: Scientific/Engineering :: Mathematics
Classifier: Topic :: Software Development :: Libraries :: Python Modules
Classifier: Intended Audience :: Developers
Classifier: Intended Audience :: Information Technology
Classifier: Intended Audience :: Science/Research
Requires-Python: >=3.5
Requires-Dist: pandas
Requires-Dist: plotly
Requires-Dist: streamlit
